poem_parser/__init__.py
poem_parser/__main__.py
poem_parser/__version__.py
poem_parser/_parser.py
poem_parser-0.0.4.dist-info/LICENSE
poem_parser-0.0.4.dist-info/METADATA
poem_parser-0.0.4.dist-info/WHEEL
poem_parser-0.0.4.dist-info/top_level.txt
poem_parser-0.0.4.dist-info/RECORD
